ebemse.py
ebemse-0.1.dist-info/METADATA
ebemse-0.1.dist-info/WHEEL
ebemse-0.1.dist-info/top_level.txt
ebemse-0.1.dist-info/RECORD
