Metadata-Version: 2.1
Name: ebemse
Version: 0.1
Summary: A package for selecting ensemble members using entropy theory
Home-page: https://gitlab.com/adlzanchetta_phd-codes/ebemse
Author: Andre D. L. Zanchetta
Author-email: adlzanchetta@gmail.com
License: UNKNOWN
Platform: UNKNOWN
Classifier: Programming Language :: Python :: 3
Classifier: License :: OSI Approved :: MIT License
Classifier: Operating System :: OS Independent
